Metadata-Version: 1.0
Name: gauss-and-binomial
Version: 1.0.0
Summary: Gaussian and Binomial distributions
Home-page: UNKNOWN
Author: Siddharth Notani
Author-email: s.notani@outlook.com
License: UNKNOWN
Platform: UNKNOWN
